schoolInfo/__init__.py
schoolInfo/school/__init__.py
schoolInfo/school/classes/__init__.py
schoolInfo/school/classes/classes.py
schoolInfo/school/major/__init__.py
schoolInfo/school/major/major.py
schoolInfo/school/meal/__init__.py
schoolInfo/school/meal/meal.py
schoolInfo/school/schedule/__init__.py
schoolInfo/school/schedule/schedule.py
schoolInfo/school/search/__init__.py
schoolInfo/school/search/search.py
schoolInfo/school/timetable/__init__.py
schoolInfo/school/timetable/timetable.py
schoolInfo/util/__init__.py
schoolInfo/util/decorater.py
schoolInfo/util/url_manager.py
schoolInfo/util/web_find.py
schoolInfo-1.0.2.0.dist-info/LICENSE
schoolInfo-1.0.2.0.dist-info/METADATA
schoolInfo-1.0.2.0.dist-info/WHEEL
schoolInfo-1.0.2.0.dist-info/top_level.txt
schoolInfo-1.0.2.0.dist-info/RECORD
