Metadata-Version: 2.1
Name: schoolInfo
Version: 1.0.2.0
Summary: 간단하게 Neis API를 이용해보세요!
Home-page: https://github.com/sunrabbit123/school-info_python
Author: sunrabbit123
Author-email: qudwls185@naver.com
License: UNKNOWN
Platform: UNKNOWN
Classifier: License :: OSI Approved :: MIT License
Requires-Python: >=3.6
Requires-Dist: aiohttp
Requires-Dist: asyncio
Requires-Dist: pytz
